ivyanalytics/__init__.py
ivyanalytics/api_client.py
ivyanalytics/api_response.py
ivyanalytics/configuration.py
ivyanalytics/exceptions.py
ivyanalytics/py.typed
ivyanalytics/rest.py
ivyanalytics/api/__init__.py
ivyanalytics/api/conversation_api.py
ivyanalytics/api/index_api.py
ivyanalytics/api/intercom_api.py
ivyanalytics/models/__init__.py
ivyanalytics/models/api_success_response.py
ivyanalytics/models/assigned_to.py
ivyanalytics/models/author.py
ivyanalytics/models/body.py
ivyanalytics/models/conversation.py
ivyanalytics/models/conversation_created_at.py
ivyanalytics/models/conversation_data_schema.py
ivyanalytics/models/conversation_parts.py
ivyanalytics/models/conversation_schema.py
ivyanalytics/models/conversation_source.py
ivyanalytics/models/data.py
ivyanalytics/models/data_item.py
ivyanalytics/models/external_id.py
ivyanalytics/models/greeting.py
ivyanalytics/models/http_validation_error.py
ivyanalytics/models/intercom_notification_event_schema.py
ivyanalytics/models/item.py
ivyanalytics/models/message_schema.py
ivyanalytics/models/metadata.py
ivyanalytics/models/name.py
ivyanalytics/models/role_enum_schema.py
ivyanalytics/models/validation_error.py
ivyanalytics/models/validation_error_loc_inner.py
ivyanalytics/models/webhook_topics.py
ivyanalytics-0.0b0.dist-info/METADATA
ivyanalytics-0.0b0.dist-info/WHEEL
ivyanalytics-0.0b0.dist-info/top_level.txt
ivyanalytics-0.0b0.dist-info/RECORD
