Metadata-Version: 2.1
Name: ivyanalytics
Version: 0.0b0
Summary: Ivy Analytics API
Home-page: https://www.ivyanalytics.io
Author: This SDK is used to ingest data into Ivy Analytics.
Author-email: hello@ivyanalytics.io
Keywords: Ivy Analytics,Conversational Analytics
Classifier: Intended Audience :: Developers
Classifier: License :: OSI Approved :: MIT License
Classifier: Programming Language :: Python
Classifier: Programming Language :: Python :: 3
Classifier: Programming Language :: Python :: 3.7
Classifier: Topic :: Software Development :: Libraries :: Python Modules
Requires-Dist: urllib3 <2.1.0,>=1.25.3
Requires-Dist: python-dateutil
Requires-Dist: pydantic >=2
Requires-Dist: typing-extensions >=4.7.1
